{
    "classname": "SimpleHeader",
    "definitions": {
        "apis": {
            "custom": [],
            "passthrough": []
        },
        "events": {
            "custom": [],
            "passthrough": [
                {
                    "access": "Enable",
                    "group": "General",
                    "kuid": "e878aee1258142ba8b6b149862c4c538",
                    "originalPropertyKey": "onClick",
                    "propertyIndex": 1,
                    "propertyKey": "onClickLeft",
                    "pw": {
                        "access": "readwrite",
                        "category": "action",
                        "displayName": "onClickLeft",
                        "srcWidget": "flxLeftIcon",
                        "type": "action",
                        "uiRepresentation": "Label-Label-Button-Button",
                        "wType": "FlexContainer"
                    },
                    "srcWgtKUID": "d80b26b75c6e4e77953f5bad01684341",
                    "translateAtInstance": false
                }
            ]
        },
        "groups": {
            "apis": [],
            "events": [],
            "properties": [],
            "widgets": []
        },
        "properties": {
            "custom": [],
            "passthrough": [
                {
                    "access": "Enable",
                    "group": "General",
                    "kuid": "d9fea83008824e38b0df80b14aa2f5ec",
                    "originalPropertyKey": "text",
                    "propertyIndex": 1,
                    "propertyKey": "leftIcon",
                    "pw": {
                        "access": "readwrite",
                        "category": "look",
                        "dependencyConditions": {},
                        "dependentKeysKUIDs": null,
                        "displayName": "leftIcon",
                        "isHiddenInTool": false,
                        "srcWidget": "lblLeftIcon",
                        "type": "string",
                        "uiRepresentation": "Label-Textbox",
                        "wType": "Label"
                    },
                    "srcWgtKUID": "a86f4de0a23d465c910d80b2a5e3ef0b"
                },
                {
                    "access": "Enable",
                    "group": "General",
                    "kuid": "e8ef505599904a99bd91aa1b155d9286",
                    "originalPropertyKey": "text",
                    "propertyIndex": 2,
                    "propertyKey": "title",
                    "pw": {
                        "access": "readwrite",
                        "category": "look",
                        "dependencyConditions": {},
                        "dependentKeysKUIDs": null,
                        "displayName": "title",
                        "isHiddenInTool": false,
                        "srcWidget": "lblTitle",
                        "type": "string",
                        "uiRepresentation": "Label-Textbox",
                        "wType": "Label"
                    },
                    "srcWgtKUID": "g9d6e31ea34f48da87716eac610d94a2"
                }
            ]
        },
        "widgets": {
            "expose": [],
            "passthrough": []
        }
    },
    "namespace": "com.hcl.demo.aggity",
    "version": "1.0.0"
}